ywsd/__init__.py
ywsd/busy_cache.py
ywsd/engine.py
ywsd/objects.py
ywsd/routing_cache.py
ywsd/routing_tree.py
ywsd/settings.py
ywsd/stage1.py
ywsd/stage2.py
ywsd/statistics.py
ywsd/util.py
ywsd/yate.py
ywsd-0.14.2.dist-info/licenses/LICENSE
ywsd-0.14.2.dist-info/METADATA
ywsd-0.14.2.dist-info/WHEEL
ywsd-0.14.2.dist-info/entry_points.txt
ywsd-0.14.2.dist-info/top_level.txt
ywsd-0.14.2.dist-info/RECORD
