Metadata-Version: 2.4
Name: ywsd
Version: 0.14.2
Summary: A yate routing engine for event telephone networks
Home-page: https://gitlab.rc5.de/eventphone/ywsd
Author: Garwin (Martin Lang)
Author-email: garwin@eventphone.de
License: AGPLv3+
Classifier: Programming Language :: Python :: 3
Classifier: Programming Language :: Python :: 3.11
Classifier: Programming Language :: Python :: 3.12
Classifier: Programming Language :: Python :: 3.13
Classifier: Programming Language :: Python :: 3.14
Classifier: License :: OSI Approved :: GNU Affero General Public License v3 or later (AGPLv3+)
License-File: LICENSE
Requires-Dist: aiopg
Requires-Dist: aiohttp
Requires-Dist: python-yate>=0.4
Requires-Dist: pyyaml
Requires-Dist: sqlalchemy==1.4.*
Dynamic: author
Dynamic: author-email
Dynamic: classifier
Dynamic: description
Dynamic: description-content-type
Dynamic: home-page
Dynamic: license
Dynamic: license-file
Dynamic: requires-dist
Dynamic: summary
